README.md
setup.py
jex/__init__.py
jex/__main__.py
jex/cli.py
jex.egg-info/PKG-INFO
jex.egg-info/SOURCES.txt
jex.egg-info/dependency_links.txt
jex.egg-info/entry_points.txt
jex.egg-info/requires.txt
jex.egg-info/top_level.txt