Metadata-Version: 2.1
Name: jex
Version: 0.1.2
Summary: JSON/YAML interactive explorer - no JQ
Home-page: https://github.com/hvnsweeting/jex
Author: Viet Hung Nguyen
Author-email: hvn@familug.org
License: MIT
Platform: UNKNOWN
Classifier: Environment :: Console
